[{"id":"06wIUOU-ffyGgTbrdHn08","end":90,"code":"","name":"(ИМТ 33 кг/м 2 ).","start":73,"xPath":"/ClinicalDocument/component/structuredBody/component[3]/section/text","decorCode":"symptom"},{"id":"AC18GI5zwh_ZXMqQwCHTq","end":280,"code":"","name":"сухость во рту","start":266,"xPath":"/ClinicalDocument/component/structuredBody/component[3]/section/text","decorCode":"symptom"},{"id":"Igoj-AbUBd3UkYIOZ-APK","end":287,"code":"","name":"жажду","start":282,"xPath":"/ClinicalDocument/component/structuredBody/component[3]/section/text","decorCode":"symptom"},{"id":"AFFyhA6yS0_FoolApTchJ","end":304,"code":"","name":"влагалищный зуд","start":289,"xPath":"/ClinicalDocument/component/structuredBody/component[3]/section/text","decorCode":"symptom"},{"id":"mazjalAUC6c5IIv8lBj80","end":369,"code":"","name":"повышение гликемии до 10 ммоль/л","start":337,"xPath":"/ClinicalDocument/component/structuredBody/component[3]/section/text","decorCode":"symptom"},{"id":"Pc2Z2qnLgPkqjPMy4sKiw","end":589,"code":"","name":"гликемия 6-8 ммоль/л при нерегулярном измерении в течение дня","start":528,"xPath":"/ClinicalDocument/component/structuredBody/component[3]/section/text","decorCode":"symptom"},{"id":"XGnmnoxtXJ8MkLGl48fe9","end":655,"code":"","name":"недостижением целевых показателей гликемии","start":613,"xPath":"/ClinicalDocument/component/structuredBody/component[3]/section/text","decorCode":"symptom"},{"id":"h4Qp-WLrMoSeY_e3IKKBg","end":963,"code":"","name":"гликемия до 11 ммоль/л постпрандиально.","start":924,"xPath":"/ClinicalDocument/component/structuredBody/component[3]/section/text","decorCode":"symptom"},{"id":"TcZGyHB9U7V5rrp5xu3ub","end":34,"code":"","name":"Тоны сердца приглушенные","start":10,"xPath":"/ClinicalDocument/component/structuredBody/component[4]/section/text/paragraph[4]","decorCode":"symptom"},{"id":"5fnMnBjazxxNla34DBF_I","end":121,"code":"","name":"Печень + 1 см ниже края реберной дуги","start":84,"xPath":"/ClinicalDocument/component/structuredBody/component[4]/section/text/paragraph[5]","decorCode":"symptom"},{"id":"kJ8Au","end":222,"code":"","name":"ИМТ 27 кг/м 2","start":209,"xPath":"/ClinicalDocument/component/structuredBody/component[3]/section/text","decorCode":"symptom"}]