[{"id":"0ibkLZHzoxxVlZK-uKhJI","end":26,"code":"","name":"повышение гликемии","start":8,"xPath":"/ClinicalDocument/component/structuredBody/component[3]/section/text","decorCode":"symptom"},{"id":"WZpBTsJ_EoCN-pOs4h815","end":284,"code":"","name":"гликемия 10—12 ммоль/л, в течение дня до 20 ммоль/л","start":233,"xPath":"/ClinicalDocument/component/structuredBody/component[3]/section/text","decorCode":"symptom"},{"id":"hhwpL5BTZkqntWgwwHKdB","end":375,"code":"","name":"повышение гликемии до 21 ммоль/л.","start":342,"xPath":"/ClinicalDocument/component/structuredBody/component[3]/section/text","decorCode":"symptom"},{"id":"VRJ0ksORF1yblIds9zEEX","end":446,"code":"","name":"Гликированный гемоглобин 13,4%,","start":415,"xPath":"/ClinicalDocument/component/structuredBody/component[3]/section/text","decorCode":"symptom"},{"id":"-WZ6tOCh4vSA8KWFZu8uh","end":613,"code":"","name":"глюкоза 6-7 ммоль/л","start":594,"xPath":"/ClinicalDocument/component/structuredBody/component[3]/section/text","decorCode":"symptom"},{"id":"sVtHnxLuObBhZbl-1exsh","end":860,"code":"","name":"гликемия натощак 14 ммоль/л, в течение дня до 20 ммоль/л","start":804,"xPath":"/ClinicalDocument/component/structuredBody/component[3]/section/text","decorCode":"symptom"},{"id":"p0T30cvdWkqHwWnB-tuL2","end":34,"code":"","name":"Тоны сердца приглушенные","start":10,"xPath":"/ClinicalDocument/component/structuredBody/component[4]/section/text/paragraph[6]","decorCode":"symptom"},{"id":"5lxwQ","end":762,"code":"","name":"диарея","start":756,"xPath":"/ClinicalDocument/component/structuredBody/component[3]/section/text","decorCode":"symptom"}]